{
  "generated_at": "2026-05-11T07:04:18.12879235Z",
  "count": 15,
  "results": [
    {
      "kind": "rpc",
      "url": "https://assetmantle-rpc.polkachu.com",
      "source": "polkachu",
      "probed_at": "2026-05-11T07:04:04.092224606Z",
      "ok": true,
      "block_height": 22316795,
      "network": "mantle-1",
      "node_moniker": "hello-assetmantle-relayer",
      "archive": false,
      "latency_p50_ms": 141,
      "latency_p95_ms": 340,
      "tls_issuer": "WE1",
      "tls_days_to_expiry": 66,
      "tls_trusted": true
    },
    {
      "kind": "rpc",
      "url": "https://assetmantle-rpc.publicnode.com",
      "source": "publicnode",
      "probed_at": "2026-05-11T07:04:04.092118591Z",
      "ok": true,
      "block_height": 22316794,
      "network": "mantle-1",
      "node_moniker": "Tendermint",
      "archive": false,
      "latency_p50_ms": 79,
      "latency_p95_ms": 193,
      "tls_issuer": "WE1",
      "tls_days_to_expiry": 59,
      "tls_trusted": true
    },
    {
      "kind": "rpc",
      "url": "https://assetmantle-rpc.stakerhouse.com",
      "source": "stakerhouse",
      "probed_at": "2026-05-11T07:04:04.092165851Z",
      "ok": true,
      "block_height": 22316795,
      "network": "mantle-1",
      "node_moniker": "assetmantle-relayer",
      "archive": false,
      "latency_p50_ms": 115,
      "latency_p95_ms": 452,
      "tls_issuer": "WE1",
      "tls_days_to_expiry": 41,
      "tls_trusted": true
    },
    {
      "kind": "rpc",
      "url": "https://public.stakewolle.com/cosmos/assetmantle/rpc",
      "source": "stakewolle",
      "probed_at": "2026-05-11T07:04:04.092119864Z",
      "ok": true,
      "block_height": 22316795,
      "network": "mantle-1",
      "node_moniker": "assetmantle-relayer",
      "archive": false,
      "latency_p50_ms": 257,
      "latency_p95_ms": 405,
      "tls_issuer": "WE1",
      "tls_days_to_expiry": 34,
      "tls_trusted": true
    },
    {
      "kind": "rpc",
      "url": "https://rpc-assetmantle-ia.cosmosia.notional.ventures",
      "source": "notional",
      "probed_at": "2026-05-11T07:04:04.09227316Z",
      "ok": false,
      "error": "Get \"https://rpc-assetmantle-ia.cosmosia.notional.ventures/status\": dial tcp: lookup rpc-assetmantle-ia.cosmosia.notional.ventures on 127.0.0.53:53: no such host",
      "archive": false,
      "tls_trusted": false
    },
    {
      "kind": "rpc",
      "url": "https://rpc.assetmantle.one",
      "source": "foundation",
      "notes": "canonical foundation endpoint (currently broken; this radar tracks the fix)",
      "probed_at": "2026-05-11T07:04:04.092444921Z",
      "ok": false,
      "error": "Get \"https://rpc.assetmantle.one/status\": context deadline exceeded",
      "archive": false,
      "tls_trusted": false
    },
    {
      "kind": "rest",
      "url": "https://assetmantle-api.polkachu.com",
      "source": "polkachu",
      "probed_at": "2026-05-11T07:04:04.092226095Z",
      "ok": true,
      "block_height": 22316795,
      "network": "mantle-1",
      "archive": false,
      "latency_p50_ms": 148,
      "latency_p95_ms": 431,
      "tls_issuer": "WE1",
      "tls_days_to_expiry": 66,
      "tls_trusted": true
    },
    {
      "kind": "rest",
      "url": "https://assetmantle-rest.publicnode.com",
      "source": "publicnode",
      "probed_at": "2026-05-11T07:04:04.092097353Z",
      "ok": true,
      "block_height": 22316794,
      "network": "mantle-1",
      "archive": false,
      "latency_p50_ms": 38,
      "latency_p95_ms": 152,
      "tls_issuer": "WE1",
      "tls_days_to_expiry": 59,
      "tls_trusted": true
    },
    {
      "kind": "rest",
      "url": "https://assetmantle-rest.stakerhouse.com",
      "source": "stakerhouse",
      "probed_at": "2026-05-11T07:04:04.653035907Z",
      "ok": true,
      "block_height": 22316795,
      "network": "mantle-1",
      "archive": false,
      "latency_p50_ms": 133,
      "latency_p95_ms": 468,
      "tls_issuer": "WE1",
      "tls_days_to_expiry": 41,
      "tls_trusted": true
    },
    {
      "kind": "rest",
      "url": "https://public.stakewolle.com/cosmos/assetmantle/rest",
      "source": "stakewolle",
      "probed_at": "2026-05-11T07:04:04.687498627Z",
      "ok": true,
      "block_height": 22316795,
      "network": "mantle-1",
      "archive": false,
      "latency_p50_ms": 137,
      "latency_p95_ms": 366,
      "tls_issuer": "WE1",
      "tls_days_to_expiry": 34,
      "tls_trusted": true
    },
    {
      "kind": "rest",
      "url": "https://rest-assetmantle-ia.cosmosia.notional.ventures",
      "source": "notional",
      "probed_at": "2026-05-11T07:04:04.693285508Z",
      "ok": false,
      "error": "Get \"https://rest-assetmantle-ia.cosmosia.notional.ventures/cosmos/base/tendermint/v1beta1/blocks/latest\": dial tcp: lookup rest-assetmantle-ia.cosmosia.notional.ventures on 127.0.0.53:53: no such host",
      "archive": false,
      "tls_trusted": false
    },
    {
      "kind": "rest",
      "url": "https://rest.assetmantle.one",
      "source": "foundation",
      "notes": "canonical foundation endpoint (currently broken; this radar tracks the fix)",
      "probed_at": "2026-05-11T07:04:05.128134332Z",
      "ok": false,
      "error": "Get \"https://rest.assetmantle.one/cosmos/base/tendermint/v1beta1/blocks/latest\": context deadline exceeded",
      "archive": false,
      "tls_trusted": false
    },
    {
      "kind": "grpc",
      "url": "assetmantle-grpc.polkachu.com:443",
      "source": "polkachu",
      "probed_at": "2026-05-11T07:04:05.154060095Z",
      "ok": false,
      "error": "tls dial: dial tcp 65.108.131.174:443: i/o timeout",
      "archive": false,
      "tls_trusted": false
    },
    {
      "kind": "grpc",
      "url": "assetmantle-grpc.publicnode.com:443",
      "source": "publicnode",
      "probed_at": "2026-05-11T07:04:05.234734067Z",
      "ok": true,
      "archive": false,
      "latency_p50_ms": 16,
      "tls_issuer": "WE1",
      "tls_days_to_expiry": 59,
      "tls_trusted": true
    },
    {
      "kind": "grpc",
      "url": "grpc.assetmantle.one:443",
      "source": "foundation",
      "notes": "canonical foundation endpoint",
      "probed_at": "2026-05-11T07:04:05.259837331Z",
      "ok": false,
      "error": "tls dial: dial tcp 62.3.50.132:443: i/o timeout",
      "archive": false,
      "tls_trusted": false
    }
  ]
}
